Metadata-Version: 1.1
Name: pyopenaristos
Version: 1.2
Summary: OA Python Client
Home-page: https://www.advantisolutions.com/
Author: Isaac Elbaz
Author-email: isaac.elbaz@advantisolutions.com
License: UNKNOWN
Download-URL: https://github.com/Advanti/pyopenaristos/archive/1.1.tar.gz
Keywords: pyopenaristos,oa
Platform: UNKNOWN
